dnslib/__init__.py
dnslib/bimap.py
dnslib/bit.py
dnslib/buffer.py
dnslib/client.py
dnslib/digparser.py
dnslib/dns.py
dnslib/fixedresolver.py
dnslib/intercept.py
dnslib/label.py
dnslib/lex.py
dnslib/proxy.py
dnslib/ranges.py
dnslib/server.py
dnslib/shellresolver.py
dnslib/test_decode.py
dnslib/zoneresolver.py
dnslib-0.9.24.dist-info/LICENSE
dnslib-0.9.24.dist-info/METADATA
dnslib-0.9.24.dist-info/WHEEL
dnslib-0.9.24.dist-info/top_level.txt
dnslib-0.9.24.dist-info/RECORD
