Metadata-Version: 2.1
Name: dnslib
Version: 0.9.24
Summary: Simple library to encode/decode DNS wire-format packets
Home-page: https://github.com/paulc/dnslib
Author: PaulC
License: BSD
Platform: UNKNOWN
Classifier: Topic :: Internet :: Name Service (DNS)
Classifier: Programming Language :: Python :: 2
Classifier: Programming Language :: Python :: 3
